LICENSE
MANIFEST.in
README.rst
giphypop.py
setup.py
giphypop.egg-info/PKG-INFO
giphypop.egg-info/SOURCES.txt
giphypop.egg-info/dependency_links.txt
giphypop.egg-info/requires.txt
giphypop.egg-info/top_level.txt