Metadata-Version: 1.1
Name: giphypop
Version: 0.1
Summary: Python wrapper for Giphy API
Home-page: http://www.github.com/shaunduncan/giphypop/
Author: Shaun Duncan
Author-email: shaun.duncan@gmail.com
License: MIT
Keywords: python giphy api
Platform: UNKNOWN
Classifier: Development Status :: 4 - Beta
Classifier: Intended Audience :: Developers
Classifier: License :: OSI Approved :: MIT License
Classifier: Operating System :: OS Independent
Classifier: Programming Language :: Python
Classifier: Topic :: Software Development :: Libraries :: Python Modules
